{"fantasy_positions":["DL"],"news_updated":1552512058052,"full_name":"Mitch Unrein","sport":"nfl","swish_id":null,"last_name":"Unrein","search_full_name":"mitchunrein","active":false,"college":"Wyoming","hashtag":"#mitchunrein-NFL-FA-98","birth_country":null,"status":"Inactive","team_changed_at":null,"search_rank":9999999,"sportradar_id":"d867198a-36ec-4a99-9037-a093216f99d8","team_abbr":null,"high_school":"Eaton (CO)","gsis_id":"00-0027573","competitions":[],"player_id":"1006","rotoworld_id":null,"rotowire_id":7319,"first_name":"Mitch","age":33,"number":98,"height":"6'4\"","pandascore_id":null,"weight":"301","birth_city":null,"depth_chart_position":null,"fantasy_data_id":13576,"kalshi_id":null,"injury_status":null,"oddsjam_id":null,"yahoo_id":24451,"injury_body_part":null,"player_shard":"3","search_first_name":"mitch","years_exp":10,"practice_description":null,"search_last_name":"unrein","injury_start_date":null,"depth_chart_order":null,"metadata":null,"opta_id":null,"stats_id":323806,"position":"DE","practice_participation":null,"team":null,"birth_state":null,"espn_id":13860,"birth_date":"1987-03-25","injury_notes":null}