{"pandascore_id":null,"opta_id":null,"search_rank":423,"active":true,"sport":"nfl","player_id":"10940","years_exp":3,"depth_chart_position":"ROLB","metadata":{"channel_id":"1113708818308558848","genius_id":"1399133","rookie_year":"2023"},"high_school":"Saint Louis School (HI)","full_name":"Nick Herbig","status":"Active","injury_status":null,"oddsjam_id":"16F850C04C9E","team_changed_at":null,"college":"Wisconsin","rotoworld_id":null,"competitions":[],"rotowire_id":16702,"stats_id":null,"weight":"240","number":51,"last_name":"Herbig","team_abbr":null,"birth_state":null,"depth_chart_order":2,"sportradar_id":"59b7b521-a0be-4ee5-8809-362601c2c80e","news_updated":1768196732524,"team":"PIT","height":"74","hashtag":"#nickherbig-NFL-PIT-51","espn_id":null,"injury_start_date":null,"player_shard":"6","fantasy_data_id":24201,"fantasy_positions":["DL","LB"],"swish_id":1215103,"injury_notes":null,"injury_body_part":null,"practice_description":null,"age":24,"search_full_name":"nickherbig","search_first_name":"nick","gsis_id":null,"yahoo_id":null,"position":"LB","birth_date":"2001-11-21","birth_country":null,"kalshi_id":"170920ed-3e18-4353-8981-70d5a42c333b","birth_city":null,"first_name":"Nick","search_last_name":"herbig","practice_participation":null}