{"fantasy_positions":["RB"],"team_abbr":null,"stats_id":null,"active":true,"injury_status":null,"opta_id":null,"oddsjam_id":null,"first_name":"Charles","injury_notes":null,"search_full_name":"charlesmcclelland","search_last_name":"mcclelland","sportradar_id":"e7053490-e763-11ed-8199-d58dac5a4f8e","status":"Active","injury_body_part":null,"rotowire_id":16766,"search_rank":9999999,"depth_chart_order":null,"espn_id":null,"swish_id":1106975,"player_id":"11102","sport":"nfl","kalshi_id":null,"news_updated":1689883855784,"depth_chart_position":null,"years_exp":1,"practice_participation":null,"rotoworld_id":null,"search_first_name":"charles","age":24,"player_shard":"8","injury_start_date":null,"weight":"192","competitions":[],"birth_city":null,"gsis_id":null,"birth_state":null,"team_changed_at":null,"birth_date":"1999-04-10","team":null,"yahoo_id":null,"metadata":{"channel_id":"1116852651619778560"},"pandascore_id":null,"position":"RB","high_school":"Clinch County (GA)","height":"70","number":38,"fantasy_data_id":null,"practice_description":null,"college":"Cincinnati","full_name":"Charles McClelland","last_name":"McClelland","hashtag":"#charlesmcclelland-NFL-FA-38","birth_country":null}