{"pandascore_id":null,"opta_id":null,"search_rank":698,"active":true,"sport":"nfl","player_id":"11394","years_exp":2,"depth_chart_position":null,"metadata":{"channel_id":"1113708815972331520","rookie_year":"2023"},"high_school":"Santiago (CA)","full_name":"Mitchell Agude","status":"Active","injury_status":null,"oddsjam_id":"9BF46A9D1450","team_changed_at":null,"college":"Miami (FL)","rotoworld_id":null,"competitions":[],"rotowire_id":17321,"stats_id":null,"weight":"262","number":50,"last_name":"Agude","team_abbr":null,"birth_state":null,"depth_chart_order":null,"sportradar_id":"fbf61e90-f0d3-11ed-8009-87febfbad4f0","news_updated":1756196406248,"team":null,"height":"76","hashtag":"#mitchellagude-NFL-FA-50","espn_id":null,"injury_start_date":null,"player_shard":"5","fantasy_data_id":null,"fantasy_positions":["LB"],"swish_id":1215067,"injury_notes":null,"injury_body_part":null,"practice_description":null,"age":26,"search_full_name":"mitchellagude","search_first_name":"mitchell","gsis_id":null,"yahoo_id":null,"position":"LB","birth_date":"1999-03-10","birth_country":null,"kalshi_id":"5a7e80ab-a879-459a-9184-d115c7849080","birth_city":null,"first_name":"Mitchell","search_last_name":"agude","practice_participation":null}