{"fantasy_positions":["RB"],"news_updated":1769062544273,"full_name":"Damien Martinez","sport":"nfl","swish_id":null,"last_name":"Martinez","search_full_name":"damienmartinez","active":true,"college":"Miami (FL)","hashtag":"#damienmartinez-NFL-GB-26","birth_country":null,"status":"Active","team_changed_at":null,"search_rank":225,"sportradar_id":"487da97d-a1e8-4a1f-9b43-085944ea1a44","team_abbr":null,"high_school":"Lewisville (TX)","gsis_id":null,"competitions":[],"player_id":"12462","rotoworld_id":null,"rotowire_id":18528,"first_name":"Damien","age":22,"number":26,"height":"72","pandascore_id":null,"weight":"217","birth_city":null,"depth_chart_position":"RB","fantasy_data_id":26029,"kalshi_id":"09c26010-6656-4b72-a131-fe395a0f4b09","injury_status":null,"oddsjam_id":"C60773EEF4F87E17","yahoo_id":null,"injury_body_part":null,"player_shard":"4","search_first_name":"damien","years_exp":1,"practice_description":null,"search_last_name":"martinez","injury_start_date":null,"depth_chart_order":4,"metadata":{"channel_id":"1222002208715833344","genius_id":"1496403","rookie_year":"2025","source_id":"27d530a0-89e2-11ec-87d7-1329dbaf6972"},"opta_id":null,"stats_id":null,"position":"RB","practice_participation":null,"team":"GB","birth_state":null,"espn_id":null,"birth_date":"2004-01-31","injury_notes":null}