{"height":"77","college":"Arizona","sportradar_id":"874de000-586c-4999-ac12-02766563e200","yahoo_id":null,"full_name":"Tetairoa McMillan","gsis_id":null,"pandascore_id":null,"oddsjam_id":"B0EA7EB5D41D39B0","birth_date":"2003-04-05","last_name":"McMillan","active":true,"rotoworld_id":null,"injury_notes":null,"rotowire_id":18547,"team_abbr":null,"search_rank":33,"injury_start_date":null,"status":"Active","search_first_name":"tetairoa","espn_id":null,"competitions":[],"player_shard":"8","weight":"212","years_exp":1,"birth_city":null,"first_name":"Tetairoa","number":4,"kalshi_id":"4c492ad0-d908-445f-8003-8fa922ba61d4","team_changed_at":null,"stats_id":null,"practice_description":null,"search_last_name":"mcmillan","birth_country":null,"hashtag":"#tetairoamcmillan-NFL-CAR-4","fantasy_positions":["WR"],"fantasy_data_id":26054,"practice_participation":null,"depth_chart_position":"LWR","injury_status":null,"metadata":{"channel_id":"1221352994293948416","genius_id":"1485374","rookie_year":"2025","source_id":"ba5ed4e0-91e8-11ec-9587-0f8fa2cff168"},"team":"CAR","search_full_name":"tetairoamcmillan","birth_state":null,"position":"WR","sport":"nfl","injury_body_part":null,"high_school":"Servite (CA)","swish_id":null,"depth_chart_order":1,"opta_id":null,"age":22,"player_id":"12526","news_updated":1772977222734}