{"height":"74","college":"Oregon","sportradar_id":"fb38f3cd-8e90-4c41-b10e-0ed37d97c3bc","yahoo_id":null,"full_name":"Jeffrey Bassa","gsis_id":null,"pandascore_id":null,"oddsjam_id":"CC6BBEA480818C57","birth_date":"2002-09-20","last_name":"Bassa","active":true,"rotoworld_id":null,"injury_notes":null,"rotowire_id":18725,"team_abbr":null,"search_rank":9999999,"injury_start_date":null,"status":"Active","search_first_name":"jeffrey","espn_id":null,"competitions":[],"player_shard":"9","weight":"235","years_exp":1,"birth_city":null,"first_name":"Jeffrey","number":31,"kalshi_id":"3b0bf3f4-6608-49fc-bc3b-0901f33e7f38","team_changed_at":null,"stats_id":null,"practice_description":null,"search_last_name":"bassa","birth_country":null,"hashtag":"#jeffreybassa-NFL-KC-31","fantasy_positions":["LB"],"fantasy_data_id":26069,"practice_participation":null,"depth_chart_position":"LOLB","injury_status":null,"metadata":{"channel_id":"1221956887285604352","genius_id":"1500358","rookie_year":"2025"},"team":"KC","search_full_name":"jeffreybassa","birth_state":null,"position":"LB","sport":"nfl","injury_body_part":null,"high_school":"Kearns (UT)","swish_id":null,"depth_chart_order":2,"opta_id":null,"age":23,"player_id":"12672","news_updated":1746691221411}