{"fantasy_positions":["DL"],"news_updated":1745698527965,"full_name":"Ty Hamilton","sport":"nfl","swish_id":null,"last_name":"Hamilton","search_full_name":"tyhamilton","active":true,"college":"Ohio State","hashtag":"#tyhamilton-NFL-LAR-57","birth_country":null,"status":"Active","team_changed_at":null,"search_rank":9999999,"sportradar_id":"cf6d1752-4c9d-4960-ba59-74cdd16c332a","team_abbr":null,"high_school":"Pickerington Central (OH)","gsis_id":null,"competitions":[],"player_id":"12676","rotoworld_id":null,"rotowire_id":18690,"first_name":"Ty","age":23,"number":57,"height":"75","pandascore_id":null,"weight":"301","birth_city":null,"depth_chart_position":"NT","fantasy_data_id":26220,"kalshi_id":"62add637-9bbe-4558-a771-a6ea138fcfb5","injury_status":null,"oddsjam_id":"50C89992E269D55B","yahoo_id":null,"injury_body_part":null,"player_shard":"2","search_first_name":"ty","years_exp":1,"practice_description":null,"search_last_name":"hamilton","injury_start_date":null,"depth_chart_order":2,"metadata":{"channel_id":"1221956868671283201","genius_id":"1499869","rookie_year":"2025"},"opta_id":null,"stats_id":null,"position":"DT","practice_participation":null,"team":"LAR","birth_state":null,"espn_id":null,"birth_date":"2002-04-15","injury_notes":null}