{"swish_id":null,"competitions":[],"team":"NE","depth_chart_position":"ROLB","birth_city":null,"stats_id":null,"fantasy_data_id":26127,"kalshi_id":"27679566-8573-470e-9632-9dabfc8d42a8","pandascore_id":null,"sportradar_id":"84863fc2-015f-49b6-9d68-23cca7096d9c","height":"76","metadata":{"channel_id":"1221956897838473216","genius_id":"1494911","rookie_year":"2025"},"search_rank":9999999,"opta_id":null,"active":true,"search_full_name":"bradynswinson","injury_notes":null,"birth_state":null,"rotoworld_id":null,"weight":"255","fantasy_positions":["DL"],"high_school":"Chapel Hill (GA)","status":"Active","player_shard":"1","gsis_id":null,"injury_body_part":null,"practice_description":null,"full_name":"Bradyn Swinson","news_updated":1745698527966,"practice_participation":null,"first_name":"Bradyn","search_first_name":"bradyn","depth_chart_order":3,"yahoo_id":null,"injury_status":null,"rotowire_id":18660,"sport":"nfl","oddsjam_id":"E814511C48A06F27","hashtag":"#bradynswinson-NFL-NE-43","years_exp":1,"team_abbr":null,"age":23,"birth_date":"2002-07-04","injury_start_date":null,"search_last_name":"swinson","position":"DE","player_id":"12677","team_changed_at":null,"number":43,"last_name":"Swinson","birth_country":null,"college":"LSU","espn_id":null}