{"fantasy_positions":["DB"],"team_abbr":null,"stats_id":null,"active":true,"injury_status":null,"opta_id":null,"oddsjam_id":"666A9CCCAE4913D4","first_name":"Makari","injury_notes":null,"search_full_name":"makaripaige","search_last_name":"paige","sportradar_id":"d7ee8af0-247a-11f0-a1a6-433496d7f7d4","status":"Active","injury_body_part":null,"rotowire_id":19172,"search_rank":9999999,"depth_chart_order":null,"espn_id":null,"swish_id":null,"player_id":"12894","sport":"nfl","kalshi_id":"91782b5b-39d5-46f2-a06a-87304d403491","news_updated":null,"depth_chart_position":null,"years_exp":1,"practice_participation":null,"rotoworld_id":null,"search_first_name":"makari","age":23,"player_shard":"7","injury_start_date":null,"weight":"208","competitions":[],"birth_city":null,"gsis_id":null,"birth_state":null,"team_changed_at":null,"birth_date":"2002-01-11","team":null,"yahoo_id":null,"metadata":{"channel_id":"1222711904242249728","rookie_year":"2025"},"pandascore_id":null,"position":"DB","high_school":"West Bloomfield (MI)","height":"76","number":null,"fantasy_data_id":null,"practice_description":null,"college":"Michigan","full_name":"Makari Paige","last_name":"Paige","hashtag":"#makaripaige-NFL-FA","birth_country":null}