{"swish_id":null,"competitions":[],"team":null,"depth_chart_position":null,"birth_city":null,"stats_id":null,"fantasy_data_id":null,"kalshi_id":"6ff7826d-1ea7-4336-ade5-ca15a034c2d8","pandascore_id":null,"sportradar_id":"6f6b8390-254a-11f0-8e9d-d3ffb2100b07","height":"74","metadata":{"channel_id":"1223089404453584897","rookie_year":"2025"},"search_rank":9999999,"opta_id":null,"active":true,"search_full_name":"johnhumphrey","injury_notes":null,"birth_state":null,"rotoworld_id":null,"weight":"193","fantasy_positions":["DB"],"high_school":"John Muir (CA)","status":"Active","player_shard":"1","gsis_id":null,"injury_body_part":null,"practice_description":null,"full_name":"John Humphrey","news_updated":null,"practice_participation":null,"first_name":"John","search_first_name":"john","depth_chart_order":null,"yahoo_id":null,"injury_status":null,"rotowire_id":19157,"sport":"nfl","oddsjam_id":"6D154EF2C1566964","hashtag":"#johnhumphrey-NFL-FA","years_exp":1,"team_abbr":null,"age":null,"birth_date":null,"injury_start_date":null,"search_last_name":"humphrey","position":"CB","player_id":"13015","team_changed_at":null,"number":null,"last_name":"Humphrey","birth_country":null,"college":"USC","espn_id":null}