{"height":"75","college":"Brown","sportradar_id":"9d04accc-a404-406f-b93c-0878410e55a6","yahoo_id":24760,"full_name":"James Develin","gsis_id":"00-0027925","pandascore_id":null,"oddsjam_id":null,"birth_date":"1988-07-23","last_name":"Develin","active":true,"rotoworld_id":6449,"injury_notes":null,"rotowire_id":8588,"team_abbr":null,"search_rank":701,"injury_start_date":null,"status":"Injured Reserve","search_first_name":"james","espn_id":13940,"competitions":[],"player_shard":"6","weight":"255","years_exp":11,"birth_city":null,"first_name":"James","number":0,"kalshi_id":null,"team_changed_at":null,"stats_id":340282,"practice_description":null,"search_last_name":"develin","birth_country":null,"hashtag":"#jamesdevelin-NFL-FA-0","fantasy_positions":["RB"],"fantasy_data_id":14783,"practice_participation":null,"depth_chart_position":null,"injury_status":null,"metadata":{"channel_id":"1116852729856131072"},"team":null,"search_full_name":"jamesdevelin","birth_state":null,"position":"FB","sport":"nfl","injury_body_part":null,"high_school":"Boyertown Area (PA)","swish_id":null,"depth_chart_order":null,"opta_id":null,"age":33,"player_id":"1303","news_updated":1588018261151}