{"fantasy_positions":["RB"],"news_updated":1753826424768,"full_name":"Cordarrelle Patterson","sport":"nfl","swish_id":690153,"last_name":"Patterson","search_full_name":"cordarrellepatterson","active":true,"college":"Tennessee","hashtag":"#cordarrellepatterson-NFL-FA-84","birth_country":null,"status":"Active","team_changed_at":null,"search_rank":596,"sportradar_id":"da85107c-365c-4d58-90ab-479d97d798b4","team_abbr":null,"high_school":"Northwestern (SC)","gsis_id":"00-0030578","competitions":[],"player_id":"1535","rotoworld_id":8327,"rotowire_id":8792,"first_name":"Cordarrelle","age":34,"number":84,"height":"74","pandascore_id":null,"weight":"220","birth_city":null,"depth_chart_position":null,"fantasy_data_id":15150,"kalshi_id":"ee6adc57-ef5a-4e08-b5db-8f21370edd39","injury_status":null,"oddsjam_id":"99A4011D14A9","yahoo_id":26652,"injury_body_part":null,"player_shard":"2","search_first_name":"cordarrelle","years_exp":12,"practice_description":null,"search_last_name":"patterson","injury_start_date":null,"depth_chart_order":null,"metadata":{"channel_id":"1113708821567533056","rookie_year":"2013"},"opta_id":null,"stats_id":690153,"position":"RB","practice_participation":null,"team":null,"birth_state":null,"espn_id":15807,"birth_date":"1991-03-17","injury_notes":null}