{"fantasy_positions":["LB"],"team_abbr":null,"stats_id":null,"active":true,"injury_status":null,"opta_id":null,"oddsjam_id":"699FB8870036","first_name":"A.J.","injury_notes":null,"search_full_name":"ajklein","search_last_name":"klein","sportradar_id":"9342eba6-e307-4c55-a0f7-993518dd4415","status":"Active","injury_body_part":null,"rotowire_id":8942,"search_rank":9999999,"depth_chart_order":null,"espn_id":15964,"swish_id":511218,"player_id":"1547","sport":"nfl","kalshi_id":null,"news_updated":1722382233850,"depth_chart_position":null,"years_exp":11,"practice_participation":null,"rotoworld_id":8558,"search_first_name":"aj","age":32,"player_shard":"7","injury_start_date":null,"weight":"240","competitions":[],"birth_city":null,"gsis_id":"00-0030463","birth_state":null,"team_changed_at":null,"birth_date":"1991-07-30","team":null,"yahoo_id":26771,"metadata":{"channel_id":"1116852744645246976","rookie_year":"2013"},"pandascore_id":null,"position":"LB","high_school":"Kimberly (WI)","height":"73","number":52,"fantasy_data_id":15186,"practice_description":null,"college":"Iowa State","full_name":"A.J. Klein","last_name":"Klein","hashtag":"#ajklein-NFL-FA-52","birth_country":null}