{"fantasy_positions":["DB"],"team_abbr":null,"stats_id":null,"active":false,"injury_status":null,"opta_id":null,"oddsjam_id":null,"first_name":"Isaiah","injury_notes":null,"search_full_name":"isaiahfrey","search_last_name":"frey","sportradar_id":"f9ada8bd-4a6a-49ac-abad-adf5bbafbb11","status":"Inactive","injury_body_part":null,"rotowire_id":8231,"search_rank":9999999,"depth_chart_order":null,"espn_id":15084,"swish_id":null,"player_id":"1733","sport":"nfl","kalshi_id":null,"news_updated":null,"depth_chart_position":null,"years_exp":3,"practice_participation":null,"rotoworld_id":null,"search_first_name":"isaiah","age":28,"player_shard":"0","injury_start_date":null,"weight":"190","competitions":[],"birth_city":null,"gsis_id":null,"birth_state":null,"team_changed_at":null,"birth_date":"1990-04-06","team":null,"yahoo_id":25894,"metadata":null,"pandascore_id":null,"position":"FS","high_school":null,"height":"5'11\"","number":23,"fantasy_data_id":15680,"practice_description":null,"college":"Nevada","full_name":"Isaiah Frey","last_name":"Frey","hashtag":"#isaiahfrey-NFL-FA-23","birth_country":null}