{"fantasy_positions":["TE"],"team_abbr":null,"stats_id":555648,"active":true,"injury_status":null,"opta_id":null,"oddsjam_id":"1D2428228DCB","first_name":"Jordan","injury_notes":null,"search_full_name":"jordanmatthews","search_last_name":"matthews","sportradar_id":"7b96a836-666b-47b6-a0a7-9dbb0b4c53e8","status":"Active","injury_body_part":null,"rotowire_id":9273,"search_rank":9999999,"depth_chart_order":null,"espn_id":16763,"swish_id":555648,"player_id":"1800","sport":"nfl","kalshi_id":null,"news_updated":1747072235199,"depth_chart_position":null,"years_exp":11,"practice_participation":null,"rotoworld_id":9420,"search_first_name":"jordan","age":32,"player_shard":"4","injury_start_date":null,"weight":"236","competitions":[],"birth_city":null,"gsis_id":"00-0031299","birth_state":null,"team_changed_at":null,"birth_date":"1992-07-16","team":null,"yahoo_id":27570,"metadata":{"channel_id":"1113708884209463296","rookie_year":"2014"},"pandascore_id":null,"position":"TE","high_school":"Madison Academy (AL)","height":"75","number":81,"fantasy_data_id":15974,"practice_description":null,"college":"Vanderbilt","full_name":"Jordan Matthews","last_name":"Matthews","hashtag":"#jordanmatthews-NFL-FA-81","birth_country":null}