{"pandascore_id":null,"opta_id":null,"search_rank":9999999,"active":true,"sport":"nfl","player_id":"1815","years_exp":8,"depth_chart_position":null,"metadata":{"channel_id":"1116852761376325632"},"high_school":"Stephenson (GA)","full_name":"Kenny Ladler","status":"Active","injury_status":null,"oddsjam_id":null,"team_changed_at":null,"college":"Vanderbilt","rotoworld_id":null,"competitions":[],"rotowire_id":9299,"stats_id":null,"weight":"200","number":32,"last_name":"Ladler","team_abbr":null,"birth_state":null,"depth_chart_order":null,"sportradar_id":"d452a634-8f68-4bae-808d-5ce4d9630970","news_updated":1581711651814,"team":null,"height":"73","hashtag":"#kennyladler-NFL-FA-32","espn_id":17317,"injury_start_date":null,"player_shard":"5","fantasy_data_id":16000,"fantasy_positions":["DB"],"swish_id":null,"injury_notes":null,"injury_body_part":null,"practice_description":null,"age":29,"search_full_name":"kennyladler","search_first_name":"kenny","gsis_id":"00-0030908","yahoo_id":28153,"position":"FS","birth_date":"1992-06-23","birth_country":null,"kalshi_id":null,"birth_city":null,"first_name":"Kenny","search_last_name":"ladler","practice_participation":null}