{"swish_id":null,"competitions":[],"team":null,"depth_chart_position":null,"birth_city":null,"stats_id":null,"fantasy_data_id":16286,"kalshi_id":null,"pandascore_id":null,"sportradar_id":"b14efdf2-c352-4659-9740-b1aed6ecd79e","height":"6'0\"","metadata":null,"search_rank":9999999,"opta_id":null,"active":false,"search_full_name":"jordansullen","injury_notes":null,"birth_state":null,"rotoworld_id":null,"weight":"200","fantasy_positions":["DB"],"high_school":null,"status":"Inactive","player_shard":"8","gsis_id":null,"injury_body_part":null,"practice_description":null,"full_name":"Jordan Sullen","news_updated":null,"practice_participation":null,"first_name":"Jordan","search_first_name":"jordan","depth_chart_order":null,"yahoo_id":null,"injury_status":null,"rotowire_id":null,"sport":"nfl","oddsjam_id":null,"hashtag":"#jordansullen-NFL-FA-42","years_exp":1,"team_abbr":null,"age":27,"birth_date":"1990-06-25","injury_start_date":null,"search_last_name":"sullen","position":"CB","player_id":"2010","team_changed_at":null,"number":42,"last_name":"Sullen","birth_country":null,"college":"Tulane","espn_id":17043}