{"height":"6'7\"","college":"Michigan State","sportradar_id":"a5210045-10f8-4f59-9547-675fd0f27840","yahoo_id":8935,"full_name":"Kellen Davis","gsis_id":null,"pandascore_id":null,"oddsjam_id":null,"birth_date":"1985-10-11","last_name":"Davis","active":false,"rotoworld_id":null,"injury_notes":null,"rotowire_id":5787,"team_abbr":null,"search_rank":9999999,"injury_start_date":null,"status":"Inactive","search_first_name":"kellen","espn_id":11392,"competitions":[],"player_shard":"5","weight":"265","years_exp":12,"birth_city":null,"first_name":"Kellen","number":47,"kalshi_id":null,"team_changed_at":null,"stats_id":264657,"practice_description":null,"search_last_name":"davis","birth_country":null,"hashtag":"#kellendavis-NFL-FA-47","fantasy_positions":["TE"],"fantasy_data_id":8142,"practice_participation":null,"depth_chart_position":null,"injury_status":null,"metadata":null,"team":null,"search_full_name":"kellendavis","birth_state":null,"position":"TE","sport":"nfl","injury_body_part":null,"high_school":"Adrian (MI)","swish_id":null,"depth_chart_order":null,"opta_id":null,"age":34,"player_id":"328","news_updated":null}