{"fantasy_positions":["LB"],"team_abbr":null,"stats_id":null,"active":false,"injury_status":null,"opta_id":null,"oddsjam_id":null,"first_name":"Chris","injury_notes":null,"search_full_name":"chrislandrum","search_last_name":"landrum","sportradar_id":"b6e1d56a-8fc4-4ea7-a88e-52f281c6d4ba","status":"Inactive","injury_body_part":null,"rotowire_id":11476,"search_rank":9999999,"depth_chart_order":null,"espn_id":2574558,"swish_id":null,"player_id":"3537","sport":"nfl","kalshi_id":null,"news_updated":1594772111496,"depth_chart_position":null,"years_exp":6,"practice_participation":null,"rotoworld_id":null,"search_first_name":"chris","age":29,"player_shard":"8","injury_start_date":null,"weight":"245","competitions":[],"birth_city":null,"gsis_id":"00-0032905","birth_state":null,"team_changed_at":null,"birth_date":"1992-09-14","team":null,"yahoo_id":29522,"metadata":null,"pandascore_id":null,"position":"OLB","high_school":"Sweet Water (AL)","height":"74","number":42,"fantasy_data_id":18304,"practice_description":null,"college":"Jacksonville State","full_name":"Chris Landrum","last_name":"Landrum","hashtag":"#chrislandrum-NFL-FA-42","birth_country":null}