{"fantasy_positions":["WR"],"news_updated":null,"full_name":"Brandon Lloyd","sport":"nfl","swish_id":null,"last_name":"Lloyd","search_full_name":"brandonlloyd","active":false,"college":"Illinois","hashtag":"#brandonlloyd-NFL-FA-84","birth_country":null,"status":"Inactive","team_changed_at":null,"search_rank":9999999,"sportradar_id":"aff54abb-40bc-4a14-8569-62d25a12fa0d","team_abbr":null,"high_school":null,"gsis_id":null,"competitions":[],"player_id":"386","rotoworld_id":null,"rotowire_id":null,"first_name":"Brandon","age":36,"number":84,"height":"6'0\"","pandascore_id":null,"weight":"188","birth_city":null,"depth_chart_position":null,"fantasy_data_id":8694,"kalshi_id":null,"injury_status":null,"oddsjam_id":null,"yahoo_id":null,"injury_body_part":null,"player_shard":"1","search_first_name":"brandon","years_exp":11,"practice_description":null,"search_last_name":"lloyd","injury_start_date":null,"depth_chart_order":null,"metadata":null,"opta_id":null,"stats_id":null,"position":"WR","practice_participation":null,"team":null,"birth_state":null,"espn_id":4582,"birth_date":"1981-07-05","injury_notes":null}