{"swish_id":null,"competitions":[],"team":null,"depth_chart_position":null,"birth_city":null,"stats_id":824442,"fantasy_data_id":18731,"kalshi_id":null,"pandascore_id":null,"sportradar_id":"","height":"6'2\"","metadata":null,"search_rank":9999999,"opta_id":null,"active":false,"search_full_name":"mandeldixon","injury_notes":null,"birth_state":null,"rotoworld_id":null,"weight":"240","fantasy_positions":["TE"],"high_school":null,"status":"Inactive","player_shard":"7","gsis_id":null,"injury_body_part":null,"practice_description":null,"full_name":"Mandel Dixon","news_updated":null,"practice_participation":null,"first_name":"Mandel","search_first_name":"mandel","depth_chart_order":null,"yahoo_id":30035,"injury_status":null,"rotowire_id":11606,"sport":"nfl","oddsjam_id":null,"hashtag":"#mandeldixon-NFL-FA-49","years_exp":0,"team_abbr":null,"age":25,"birth_date":"1993-04-21","injury_start_date":null,"search_last_name":"dixon","position":"TE","player_id":"3905","team_changed_at":null,"number":49,"last_name":"Dixon","birth_country":null,"college":"Tulsa","espn_id":null}