{"fantasy_positions":["OL"],"team_abbr":null,"stats_id":null,"active":true,"injury_status":null,"opta_id":null,"oddsjam_id":"114DB68E9545","first_name":"Frank","injury_notes":null,"search_full_name":"frankragnow","search_last_name":"ragnow","sportradar_id":"44176cc9-9025-4dec-a790-fbfa57686a6c","status":"Active","injury_body_part":null,"rotowire_id":12888,"search_rank":9999999,"depth_chart_order":null,"espn_id":3128689,"swish_id":837912,"player_id":"4987","sport":"nfl","kalshi_id":"168d4c02-5e18-42c7-b0c6-dbfb0bbc09e4","news_updated":1764642028886,"depth_chart_position":null,"years_exp":7,"practice_participation":null,"rotoworld_id":13116,"search_first_name":"frank","age":29,"player_shard":"2","injury_start_date":null,"weight":"310","competitions":[],"birth_city":null,"gsis_id":"00-0034345","birth_state":null,"team_changed_at":null,"birth_date":"1996-05-17","team":null,"yahoo_id":30990,"metadata":{"channel_id":"1113708811610255361","genius_id":"1005495","rookie_year":"2018"},"pandascore_id":null,"position":"C","high_school":"Chanhassen (MN)","height":"77","number":77,"fantasy_data_id":19845,"practice_description":null,"college":"Arkansas","full_name":"Frank Ragnow","last_name":"Ragnow","hashtag":"#frankragnow-NFL-FA-77","birth_country":null}