{"fantasy_positions":["TE"],"team_abbr":null,"stats_id":838256,"active":true,"injury_status":null,"opta_id":null,"oddsjam_id":null,"first_name":"Alec","injury_notes":null,"search_full_name":"alecbloom","search_last_name":"bloom","sportradar_id":"69e38370-3c00-470d-aed2-af98bcddb7c1","status":"Active","injury_body_part":null,"rotowire_id":13209,"search_rank":9999999,"depth_chart_order":null,"espn_id":3125891,"swish_id":null,"player_id":"5385","sport":"nfl","kalshi_id":null,"news_updated":null,"depth_chart_position":null,"years_exp":4,"practice_participation":null,"rotoworld_id":null,"search_first_name":"alec","age":25,"player_shard":"5","injury_start_date":null,"weight":"253","competitions":[],"birth_city":null,"gsis_id":"00-0034472","birth_state":null,"team_changed_at":null,"birth_date":"1996-04-03","team":null,"yahoo_id":31298,"metadata":{"channel_id":"1116853093779111936"},"pandascore_id":null,"position":"TE","high_school":"Ligonier Valley Senior","height":"78","number":87,"fantasy_data_id":20464,"practice_description":null,"college":"Connecticut","full_name":"Alec Bloom","last_name":"Bloom","hashtag":"#alecbloom-NFL-FA-87","birth_country":null}