{"fantasy_positions":["WR"],"team_abbr":null,"stats_id":729673,"active":true,"injury_status":null,"opta_id":null,"oddsjam_id":null,"first_name":"Mark","injury_notes":null,"search_full_name":"markchapman","search_last_name":"chapman","sportradar_id":"e2adb182-22f9-420d-8469-b84b04d9dc19","status":"Active","injury_body_part":null,"rotowire_id":13372,"search_rank":9999999,"depth_chart_order":null,"espn_id":3044693,"swish_id":null,"player_id":"5776","sport":"nfl","kalshi_id":null,"news_updated":null,"depth_chart_position":null,"years_exp":4,"practice_participation":null,"rotoworld_id":null,"search_first_name":"mark","age":null,"player_shard":"0","injury_start_date":null,"weight":"180","competitions":[],"birth_city":null,"gsis_id":"00-0034861","birth_state":null,"team_changed_at":null,"birth_date":null,"team":null,"yahoo_id":31773,"metadata":{"channel_id":"1116853161609396224"},"pandascore_id":null,"position":"WR","high_school":"Port Huron","height":"72","number":85,"fantasy_data_id":20681,"practice_description":null,"college":"Central Michigan","full_name":"Mark Chapman","last_name":"Chapman","hashtag":"#markchapman-NFL-FA-85","birth_country":null}