{"fantasy_positions":["DL"],"team_abbr":null,"stats_id":null,"active":true,"injury_status":null,"opta_id":null,"oddsjam_id":null,"first_name":"Nathan","injury_notes":null,"search_full_name":"nathanbazata","search_last_name":"bazata","sportradar_id":"dd20b476-52fe-48e1-a614-3854c6b3989c","status":"Active","injury_body_part":null,"rotowire_id":13387,"search_rank":9999999,"depth_chart_order":null,"espn_id":3040172,"swish_id":null,"player_id":"5789","sport":"nfl","kalshi_id":null,"news_updated":null,"depth_chart_position":null,"years_exp":4,"practice_participation":null,"rotoworld_id":null,"search_first_name":"nathan","age":27,"player_shard":"7","injury_start_date":null,"weight":"287","competitions":[],"birth_city":null,"gsis_id":"00-0034880","birth_state":null,"team_changed_at":null,"birth_date":"1994-07-15","team":null,"yahoo_id":31788,"metadata":{"channel_id":"1116853164172115968"},"pandascore_id":null,"position":"DT","high_school":"Howells-Dodge","height":"74","number":73,"fantasy_data_id":20691,"practice_description":null,"college":"Iowa","full_name":"Nathan Bazata","last_name":"Bazata","hashtag":"#nathanbazata-NFL-FA-73","birth_country":null}