{"swish_id":820884,"competitions":[],"team":null,"depth_chart_position":null,"birth_city":null,"stats_id":null,"fantasy_data_id":20915,"kalshi_id":"cfc05851-7cd1-436a-a426-6c5176a08384","pandascore_id":null,"sportradar_id":"ac012bab-43f3-4e8c-9cf4-0fb20ffa55a2","height":"75","metadata":{"channel_id":"1113708807529197568","genius_id":"1021078","rookie_year":"2019"},"search_rank":466,"opta_id":null,"active":true,"search_full_name":"germainepratt","injury_notes":null,"birth_state":null,"rotoworld_id":null,"weight":"250","fantasy_positions":["LB"],"high_school":"High Point Central (NC)","status":"Active","player_shard":"7","gsis_id":" 00-0035697","injury_body_part":null,"practice_description":null,"full_name":"Germaine Pratt","news_updated":1767717612328,"practice_participation":null,"first_name":"Germaine","search_first_name":"germaine","depth_chart_order":null,"yahoo_id":31904,"injury_status":null,"rotowire_id":13436,"sport":"nfl","oddsjam_id":"4DFC04F4EA02","hashtag":"#germainepratt-NFL-FA-53","years_exp":7,"team_abbr":null,"age":29,"birth_date":"1996-05-21","injury_start_date":null,"search_last_name":"pratt","position":"LB","player_id":"5894","team_changed_at":null,"number":53,"last_name":"Pratt","birth_country":null,"college":"North Carolina State","espn_id":3116724}