{"pandascore_id":null,"opta_id":null,"search_rank":9999999,"active":true,"sport":"nfl","player_id":"6042","years_exp":3,"depth_chart_position":null,"metadata":{"channel_id":"1116853192714354688"},"high_school":"Booker T. Washington","full_name":"Davante Davis","status":"Active","injury_status":null,"oddsjam_id":null,"team_changed_at":null,"college":"Texas","rotoworld_id":null,"competitions":[],"rotowire_id":13849,"stats_id":null,"weight":"205","number":0,"last_name":"Davis","team_abbr":null,"birth_state":null,"depth_chart_order":null,"sportradar_id":"0553c32c-4b9d-4ea9-811d-6d58c1985c9b","news_updated":1574206250534,"team":null,"height":"74","hashtag":"#davantedavis-NFL-FA-0","espn_id":3929849,"injury_start_date":null,"player_shard":"1","fantasy_data_id":21058,"fantasy_positions":["DB"],"swish_id":null,"injury_notes":null,"injury_body_part":null,"practice_description":null,"age":26,"search_full_name":"davantedavis","search_first_name":"davante","gsis_id":" 00-0035088","yahoo_id":32331,"position":"CB","birth_date":"1995-09-26","birth_country":null,"kalshi_id":null,"birth_city":null,"first_name":"Davante","search_last_name":"davis","practice_participation":null}