{"fantasy_positions":["OL"],"team_abbr":null,"stats_id":null,"active":true,"injury_status":null,"opta_id":null,"oddsjam_id":null,"first_name":"Lamont","injury_notes":null,"search_full_name":"lamontgaillard","search_last_name":"gaillard","sportradar_id":"0c8b0581-9ed2-488b-bcaa-ef783261dfd1","status":"Active","injury_body_part":null,"rotowire_id":13678,"search_rank":9999999,"depth_chart_order":null,"espn_id":3128707,"swish_id":822861,"player_id":"6058","sport":"nfl","kalshi_id":null,"news_updated":1666799425140,"depth_chart_position":null,"years_exp":3,"practice_participation":null,"rotoworld_id":null,"search_first_name":"lamont","age":26,"player_shard":"7","injury_start_date":null,"weight":"305","competitions":[],"birth_city":null,"gsis_id":" 00-0035536","birth_state":null,"team_changed_at":null,"birth_date":"1996-02-08","team":null,"yahoo_id":32011,"metadata":{"channel_id":"1116853195864276992"},"pandascore_id":null,"position":"C","high_school":"Pine Forest (NC)","height":"75","number":61,"fantasy_data_id":20763,"practice_description":null,"college":"Georgia","full_name":"Lamont Gaillard","last_name":"Gaillard","hashtag":"#lamontgaillard-NFL-FA-61","birth_country":null}