{"swish_id":839068,"competitions":[],"team":"KC","depth_chart_position":"LOLB","birth_city":null,"stats_id":null,"fantasy_data_id":20968,"kalshi_id":"c8e85860-11a4-4e12-8e40-e9e080f6b865","pandascore_id":null,"sportradar_id":"d468dfe5-8ad2-4c8b-b7ba-0962316a2156","height":"74","metadata":{"channel_id":"1113708752512512001","genius_id":"1009841","rookie_year":"2019"},"search_rank":999,"opta_id":null,"active":true,"search_full_name":"druetranquill","injury_notes":null,"birth_state":null,"rotoworld_id":null,"weight":"234","fantasy_positions":["LB"],"high_school":"Carroll (IN)","status":"Active","player_shard":"4","gsis_id":" 00-0035262","injury_body_part":null,"practice_description":null,"full_name":"Drue Tranquill","news_updated":1773374748341,"practice_participation":null,"first_name":"Drue","search_first_name":"drue","depth_chart_order":1,"yahoo_id":31962,"injury_status":null,"rotowire_id":13814,"sport":"nfl","oddsjam_id":"6A4953F42726","hashtag":"#druetranquill-NFL-KC-23","years_exp":7,"team_abbr":null,"age":30,"birth_date":"1995-08-15","injury_start_date":null,"search_last_name":"tranquill","position":"LB","player_id":"6141","team_changed_at":null,"number":23,"last_name":"Tranquill","birth_country":null,"college":"Notre Dame","espn_id":3129310}