{"pandascore_id":null,"opta_id":null,"search_rank":9999999,"active":true,"sport":"nfl","player_id":"6301","years_exp":7,"depth_chart_position":null,"metadata":{"channel_id":"1113708883022475264","genius_id":"1007938","rookie_year":"2019"},"high_school":"Fairfax (VA)","full_name":"Nick Scott","status":"Active","injury_status":null,"oddsjam_id":"94AF5BE90AE0","team_changed_at":null,"college":"Penn State","rotoworld_id":null,"competitions":[],"rotowire_id":13958,"stats_id":null,"weight":"200","number":21,"last_name":"Scott","team_abbr":null,"birth_state":null,"depth_chart_order":null,"sportradar_id":"4d383922-53ab-48f8-bb8a-29176ea3ffbc","news_updated":1773594329741,"team":"CAR","height":"71","hashtag":"#nickscott-NFL-CAR-21","espn_id":3116179,"injury_start_date":null,"player_shard":"8","fantasy_data_id":21131,"fantasy_positions":["DB"],"swish_id":836171,"injury_notes":null,"injury_body_part":null,"practice_description":null,"age":30,"search_full_name":"nickscott","search_first_name":"nick","gsis_id":" 00-0035669","yahoo_id":32075,"position":"DB","birth_date":"1995-05-17","birth_country":null,"kalshi_id":"f6d66a2e-4c93-4293-abdd-48646cc7351b","birth_city":null,"first_name":"Nick","search_last_name":"scott","practice_participation":null}