{"pandascore_id":null,"opta_id":null,"search_rank":9999999,"active":true,"sport":"nfl","player_id":"7035","years_exp":2,"depth_chart_position":null,"metadata":{"channel_id":"1116853325392773120"},"high_school":"Frankston (TX)","full_name":"Kendrick Rogers","status":"Active","injury_status":null,"oddsjam_id":null,"team_changed_at":null,"college":"Texas A&M","rotoworld_id":null,"competitions":[],"rotowire_id":14490,"stats_id":null,"weight":"204","number":16,"last_name":"Rogers","team_abbr":null,"birth_state":null,"depth_chart_order":null,"sportradar_id":"2c80896a-fa23-4581-b7d0-b34c35268404","news_updated":1596992449775,"team":null,"height":"76","hashtag":"#kendrickrogers-NFL-FA-16","espn_id":null,"injury_start_date":null,"player_shard":"2","fantasy_data_id":21757,"fantasy_positions":["WR"],"swish_id":null,"injury_notes":null,"injury_body_part":null,"practice_description":null,"age":24,"search_full_name":"kendrickrogers","search_first_name":"kendrick","gsis_id":null,"yahoo_id":33097,"position":"WR","birth_date":"1997-08-07","birth_country":null,"kalshi_id":null,"birth_city":null,"first_name":"Kendrick","search_last_name":"rogers","practice_participation":null}