{"fantasy_positions":["DB"],"news_updated":1634101504847,"full_name":"Tyrique McGhee","sport":"nfl","swish_id":null,"last_name":"McGhee","search_full_name":"tyriquemcghee","active":true,"college":"Georgia","hashtag":"#tyriquemcghee-NFL-FA-0","birth_country":null,"status":"Active","team_changed_at":null,"search_rank":9999999,"sportradar_id":"22666f2a-8d3f-45ed-9cc6-3349f838291d","team_abbr":null,"high_school":"Peach County (GA)","gsis_id":null,"competitions":[],"player_id":"7349","rotoworld_id":null,"rotowire_id":15089,"first_name":"Tyrique","age":23,"number":0,"height":"70","pandascore_id":null,"weight":"187","birth_city":null,"depth_chart_position":null,"fantasy_data_id":22337,"kalshi_id":null,"injury_status":null,"oddsjam_id":null,"yahoo_id":33257,"injury_body_part":null,"player_shard":"5","search_first_name":"tyrique","years_exp":2,"practice_description":null,"search_last_name":"mcghee","injury_start_date":null,"depth_chart_order":null,"metadata":{"channel_id":"1116853372897460224"},"opta_id":null,"stats_id":null,"position":"DB","practice_participation":null,"team":null,"birth_state":null,"espn_id":4035013,"birth_date":"1998-08-11","injury_notes":null}