{"fantasy_positions":["P"],"news_updated":1649957715076,"full_name":"Hunter Niswander","sport":"nfl","swish_id":742459,"last_name":"Niswander","search_full_name":"hunterniswander","active":true,"college":"Northwestern","hashtag":"#hunterniswander-NFL-DAL-7","birth_country":null,"status":"Active","team_changed_at":null,"search_rank":9999999,"sportradar_id":"48efc038-96b7-4c63-a33c-41f6abe6d3de","team_abbr":null,"high_school":"Woodridge (OH)","gsis_id":null,"competitions":[],"player_id":"7516","rotoworld_id":null,"rotowire_id":15206,"first_name":"Hunter","age":27,"number":7,"height":"77","pandascore_id":null,"weight":"243","birth_city":null,"depth_chart_position":null,"fantasy_data_id":null,"kalshi_id":null,"injury_status":null,"oddsjam_id":null,"yahoo_id":null,"injury_body_part":null,"player_shard":"4","search_first_name":"hunter","years_exp":2,"practice_description":null,"search_last_name":"niswander","injury_start_date":null,"depth_chart_order":null,"metadata":{"channel_id":"1116853401401950208"},"opta_id":null,"stats_id":null,"position":"P","practice_participation":null,"team":"DAL","birth_state":null,"espn_id":null,"birth_date":"1994-11-26","injury_notes":null}