{"fantasy_positions":["WR"],"team_abbr":null,"stats_id":null,"active":true,"injury_status":null,"opta_id":null,"oddsjam_id":"F14F275570BD","first_name":"Ihmir","injury_notes":null,"search_full_name":"ihmirsmithmarsette","search_last_name":"smithmarsette","sportradar_id":"39156891-0d05-470b-8b64-751602820bb1","status":"Active","injury_body_part":null,"rotowire_id":15287,"search_rank":241,"depth_chart_order":10,"espn_id":null,"swish_id":1059221,"player_id":"7559","sport":"nfl","kalshi_id":"f97c93ac-60a6-41fa-963f-d4df43fc1c60","news_updated":1768541417261,"depth_chart_position":"SWR","years_exp":5,"practice_participation":null,"rotoworld_id":null,"search_first_name":"ihmir","age":26,"player_shard":"1","injury_start_date":null,"weight":"185","competitions":[],"birth_city":null,"gsis_id":null,"birth_state":null,"team_changed_at":null,"birth_date":"1999-08-29","team":"ARI","yahoo_id":null,"metadata":{"channel_id":"1113708882271694848","genius_id":"1006833","rookie_year":"2021"},"pandascore_id":null,"position":"WR","high_school":"Weequahic (NJ)","height":"73","number":87,"fantasy_data_id":22595,"practice_description":null,"college":"Iowa","full_name":"Ihmir Smith-Marsette","last_name":"Smith-Marsette","hashtag":"#ihmirsmithmarsette-NFL-ARI-87","birth_country":null}