{"height":"72","college":"Illinois","sportradar_id":"b34aa9fb-3f93-481b-8f68-7330c39e6e20","yahoo_id":null,"full_name":"Nate Hobbs","gsis_id":null,"pandascore_id":null,"oddsjam_id":"AB1443A71C5D","birth_date":"1999-06-24","last_name":"Hobbs","active":true,"rotoworld_id":null,"injury_notes":null,"rotowire_id":15387,"team_abbr":null,"search_rank":9999999,"injury_start_date":null,"status":"Active","search_first_name":"nate","espn_id":null,"competitions":[],"player_shard":"5","weight":"195","years_exp":5,"birth_city":null,"first_name":"Nate","number":21,"kalshi_id":"334cbf45-eaf4-4f14-97db-5c588aadfefd","team_changed_at":null,"stats_id":null,"practice_description":null,"search_last_name":"hobbs","birth_country":null,"hashtag":"#natehobbs-NFL-SF-21","fantasy_positions":["DB"],"fantasy_data_id":22921,"practice_participation":null,"depth_chart_position":"DB","injury_status":null,"metadata":{"channel_id":"1113708771990859776","genius_id":"1007803","rookie_year":"2021"},"team":"SF","search_full_name":"natehobbs","birth_state":null,"position":"CB","sport":"nfl","injury_body_part":null,"high_school":"Louisville Male (KY)","swish_id":1057536,"depth_chart_order":null,"opta_id":null,"age":26,"player_id":"7823","news_updated":1773375347989}