{"pandascore_id":null,"opta_id":null,"search_rank":9999999,"active":true,"sport":"nfl","player_id":"8185","years_exp":3,"depth_chart_position":null,"metadata":{"channel_id":"1113708789153951745","rookie_year":"2022"},"high_school":"Chandler (AZ)","full_name":"Johnny Johnson","status":"Inactive","injury_status":null,"oddsjam_id":"66A01576F4FA","team_changed_at":null,"college":"Oregon","rotoworld_id":null,"competitions":[],"rotowire_id":16031,"stats_id":null,"weight":"199","number":88,"last_name":"Johnson","team_abbr":null,"birth_state":null,"depth_chart_order":null,"sportradar_id":"ef986840-c967-11ec-89b7-476565ea032f","news_updated":1765925445509,"team":null,"height":"73","hashtag":"#johnnyjohnson-NFL-FA-88","espn_id":null,"injury_start_date":null,"player_shard":"4","fantasy_data_id":null,"fantasy_positions":["WR"],"swish_id":1060285,"injury_notes":null,"injury_body_part":null,"practice_description":null,"age":26,"search_full_name":"johnnyjohnson","search_first_name":"johnny","gsis_id":null,"yahoo_id":null,"position":"WR","birth_date":"1999-05-04","birth_country":null,"kalshi_id":"c60dc83d-82b4-4b34-8450-ba81e2af7b89","birth_city":null,"first_name":"Johnny","search_last_name":"johnson","practice_participation":null}