{"pandascore_id":null,"opta_id":null,"search_rank":9999999,"active":true,"sport":"nfl","player_id":"8494","years_exp":4,"depth_chart_position":"LOLB","metadata":{"channel_id":"1113708812633665536","genius_id":"1007507","rookie_year":"2022"},"high_school":"American Heritage (FL)","full_name":"James Houston","status":"Active","injury_status":null,"oddsjam_id":"B65A0841372E","team_changed_at":null,"college":"Jackson State","rotoworld_id":null,"competitions":[],"rotowire_id":16281,"stats_id":null,"weight":"241","number":53,"last_name":"Houston","team_abbr":null,"birth_state":null,"depth_chart_order":1,"sportradar_id":"6f9be289-1bfa-46b8-b246-57adb586c641","news_updated":1770519601620,"team":"DAL","height":"73","hashtag":"#jameshouston-NFL-DAL-53","espn_id":null,"injury_start_date":null,"player_shard":"9","fantasy_data_id":23617,"fantasy_positions":["DL","LB"],"swish_id":974827,"injury_notes":null,"injury_body_part":null,"practice_description":null,"age":27,"search_full_name":"jameshouston","search_first_name":"james","gsis_id":null,"yahoo_id":null,"position":"LB","birth_date":"1998-11-16","birth_country":null,"kalshi_id":"9e8e8319-d605-4933-86d5-559778eafe55","birth_city":null,"first_name":"James","search_last_name":"houston","practice_participation":null}