{"pandascore_id":null,"opta_id":null,"search_rank":200,"active":true,"sport":"nfl","player_id":"9486","years_exp":3,"depth_chart_position":"LWR","metadata":{"channel_id":"1113708802848354304","genius_id":"1399228","rookie_year":"2023"},"high_school":"Plaquemine (LA)","full_name":"Dontayvion Wicks","status":"Active","injury_status":null,"oddsjam_id":"A600F04E54A1","team_changed_at":null,"college":"Virginia","rotoworld_id":null,"competitions":[],"rotowire_id":16658,"stats_id":null,"weight":"206","number":13,"last_name":"Wicks","team_abbr":null,"birth_state":null,"depth_chart_order":3,"sportradar_id":"ea3d1393-8c3b-4e81-a519-f636d28d692e","news_updated":1772140508886,"team":"GB","height":"73","hashtag":"#dontayvionwicks-NFL-GB-13","espn_id":null,"injury_start_date":null,"player_shard":"9","fantasy_data_id":23253,"fantasy_positions":["WR"],"swish_id":1172428,"injury_notes":null,"injury_body_part":null,"practice_description":null,"age":24,"search_full_name":"dontayvionwicks","search_first_name":"dontayvion","gsis_id":null,"yahoo_id":null,"position":"WR","birth_date":"2001-06-16","birth_country":null,"kalshi_id":"d9fe1c12-01bb-4569-bea7-31fb1180b168","birth_city":null,"first_name":"Dontayvion","search_last_name":"wicks","practice_participation":null}